Nghị_định số 34/2024/nđ-cp ngày 31 tháng 03 năm 2024 của chính_phủ

Căn_cứ <LT rel="CC"> Luật Tổ_chức Chính_phủ ngày 19 tháng 6 năm 2015 </LT> ; Luật sửa_đổi , bổ_sung một_số điều của <LT rel="CC"> Luật Tổ_chức Chính_phủ và </LT> <LT rel="None"> Luật Tổ_chức chính_quyền địa_phương ngày 22 tháng 11 năm 2019 </LT> ;

Căn_cứ <LT rel="CC"> Luật Giao_thông đường_bộ ngày 13 tháng 11 năm 2008 </LT> ;

Căn_cứ <LT rel="CC"> Luật Năng_lượng nguyên_tử ngày 03 tháng 6 năm 2008 </LT> ;

Căn_cứ <LT rel="CC"> Luật Hoá_chất ngày 29 tháng 6 năm 2018 </LT> ;

Căn_cứ <LT rel="CC"> Luật Bảo_vệ môi_trường ngày 17 tháng 11 năm 2020 </LT> ;

Căn_cứ <LT rel="CC"> Luật Giao_thông đường_thuỷ nội_địa ngày 15 tháng 6 năm 2004 </LT> ; Luật sửa_đổi , bổ_sung một_số điều của <LT rel="None"> Luật Giao_thông đường_thuỷ nội_địa ngày 17 tháng 6 năm 2014 </LT> ;

Theo đề_nghị của Bộ_trưởng Bộ Giao_thông vận_tải ;

Chính_phủ ban_hành <NĐ rel="None"> Nghị_định quy_định về Danh_mục hàng_hoá nguy_hiểm , vận_chuyển hàng_hoá nguy_hiểm bằng </NĐ> phương_tiện giao_thông cơ_giới đường_bộ và phương_tiện thuỷ nội_địa .

Chương I

Quy_định Chung

Điều 1 . Phạm_vi điều_chỉnh

1 . Nghị_định này quy_định Danh_mục hàng_hoá nguy_hiểm , việc vận_chuyển hàng_hoá nguy_hiểm , cấp Giấy_phép vận_chuyển hàng_hoá nguy_hiểm bằng phương_tiện giao_thông cơ_giới đường_bộ và vận_chuyển hàng_hoá nguy_hiểm trên đường_thuỷ nội_địa .

2 . Đối_với hoạt_động vận_chuyển các chất phóng_xạ , ngoài việc thực_hiện Nghị_định này còn phải thực_hiện theo quy_định của pháp_luật về năng_lượng nguyên_tử .

3 . Đối_với hoạt_động vận_chuyển vũ_khí , vật_liệu nổ , công_cụ hỗ_trợ , tiền chất thuốc_nổ , pháo thực_hiện theo quy_định của pháp_luật về vũ_khí , vật_liệu nổ , công_cụ hỗ_trợ , tiền chất thuốc_nổ và pháo .

4 . Đối_với hoạt_động vận_chuyển các loại hàng_hoá nguy_hiểm phục_vụ mục_đích an_ninh , quốc_phòng của lực_lượng vũ_trang thực_hiện theo quy_định của Nghị_định này và do Bộ_trưởng Bộ Công_an và Bộ_trưởng Bộ Quốc_phòng tổ_chức thực_hiện .

5 . Đối_với các hàng_hoá nguy_hiểm là chất_thải nguy_hại , ngoài quy_định của nghị_định này còn phải tuân_thủ quy_định của pháp_luật về bảo_vệ môi_trường .

6 . Đối_với trường_hợp có quy_định khác nhau giữa Nghị_định này với quy_định của pháp_luật về năng_lượng nguyên_tử , vũ_khí , vật_liệu nổ , công_cụ hỗ_trợ , tiền chất thuốc_nổ , pháo , bảo_vệ môi_trường , phòng cháy và chữa_cháy thì thực_hiện theo quy_định của pháp_luật về năng_lượng nguyên_tử , vũ_khí , vật_liệu nổ , công_cụ hỗ_trợ , tiền chất thuốc_nổ và pháo , bảo_vệ môi_trường , phòng cháy và chữa_cháy .

Điều 2 . Đối_tượng áp_dụng

1 . Nghị_định này áp_dụng với tổ_chức , cá_nhân Việt_nam và nước_ngoài liên_quan đến việc vận_chuyển hàng_hoá nguy_hiểm bằng phương_tiện giao_thông cơ_giới đường_bộ và trên đường_thuỷ nội_địa trên lãnh_thổ nước Cộng_hoà xã_hội chủ_nghĩa Việt_nam .

2 . Thủ_tướng Chính_phủ Quyết_định việc áp_dụng những quy_chế , biện_pháp đặc_biệt đối_với việc vận_chuyển hàng_hoá nguy_hiểm trong các trường_hợp sau đây :

a ) Hàng_hoá phục_vụ cho yêu_cầu cấp_bách phòng , chống dịch_bệnh , thiên_tai , địch_hoạ ;

b ) Hàng_hoá quá_cảnh của các nước , tổ_chức quốc_tế không kí_kết điều_ước quốc_tế liên_quan tới Việt_nam .

Điều 3 . Giải_thích từ_ngữ

Trong Nghị_định này , các từ_ngữ dưới đây được hiểu như sau :

1 . Chất nguy_hiểm là những chất hoặc hợp_chất ở dạng khí , dạng lỏng hoặc dạng rắn có khả_năng gây nguy_hại tới tính_mạng , sức_khoẻ con_người , môi_trường , an_toàn và an_ninh quốc_gia .

2 . Hàng nguy_hiểm ( hàng_hoá nguy_hiểm ) là hàng_hoá có chứa các chất nguy_hiểm khi chở trên đường_bộ hoặc đường_thuỷ nội_địa có khả_năng gây nguy_hại tới tính_mạng , sức_khoẻ con_người , môi_trường , an_toàn và an_ninh quốc_gia .

3 . Người vận_tải là tổ_chức , cá_nhân sử_dụng phương_tiện giao_thông cơ_giới đường_bộ hoặc phương_tiện thuỷ nội_địa để thực_hiện vận_chuyển hàng_hoá nguy_hiểm .

4 . Người thuê vận_tải là tổ_chức , cá_nhân giao_kết_hợp_đồng vận_tải hàng_hoá nguy_hiểm trên đường_bộ hoặc trên đường_thuỷ nội_địa với người vận_tải .

5 . Người xếp_dỡ hàng_hoá nguy_hiểm là tổ_chức , cá_nhân thực_hiện việc xếp , dỡ hàng_hoá nguy_hiểm trên phương_tiện giao_thông cơ_giới đường_bộ hoặc trên phương_tiện thuỷ nội_địa hoặc tại kho , bãi lưu_giữ hàng_hoá nguy_hiểm .

6 . Người nhận hàng_hoá nguy_hiểm là tổ_chức , cá_nhân có tên nhận hàng ghi trên giấy vận_tải ( vận_chuyển ) hàng_hoá nguy_hiểm .

7 . Người điều_khiển phương_tiện là người lái phương_tiện giao_thông cơ_giới đường_bộ hoặc thuyền_viên , người lái phương_tiện thuỷ nội_địa .

8 . Người áp_tải là cá_nhân do người thuê vận_tải ( hoặc chủ hàng ) sử_dụng để thực_hiện nhiệm_vụ áp_tải hàng_hoá nguy_hiểm trong suốt quá_trình vận_chuyển .

9 . Người thủ_kho là người chịu trách_nhiệm chính trong việc quản_lí tình_trạng , số_lượng của tất_cả các hàng_hoá từ lúc chuyển vào kho cho đến lúc hàng_hoá đó xuất đi khỏi kho .

Chương_ii

Phân_loại , Danh_mục , Đóng_gói , Dán Nhãn Và Huấn_luyện An_toàn Hàng_hóa_nguy_hiểm

Điều 4 . Phân_loại hàng_hoá nguy_hiểm

1 . Tuỳ theo tính_chất hoá , lý , hàng_hoá nguy_hiểm được phân thành 9 loại và nhóm loại sau đây :

a ) Loại 1 . Chất_nổ và vật_phẩm dễ nổ ;

Nhóm 1 . 1 : Chất và vật_phẩm có nguy_cơ nổ rộng .

Nhóm 1 . 2 : Chất và vật_phẩm có nguy_cơ bắn toé nhưng không nổ rộng .

Nhóm 1 . 3 : Chất và vật_phẩm có nguy_cơ cháy và nguy_cơ nổ nhỏ hoặc bắn toé nhỏ hoặc cả hai , nhưng không nổ rộng .

Nhóm 1 . 4 : Chất và vật_phẩm có nguy_cơ không đáng_kể .

Nhóm 1 . 5 : Chất không nhạy nhưng có nguy_cơ nổ rộng .

Nhóm 1 . 6 : Vật_phẩm đặc_biệt không nhạy , không có nguy_cơ nổ rộng .

b ) Loại 2 . Khí ;

Nhóm 2 . 1 : Khí dễ cháy .

Nhóm 2 . 2 : Khí không dễ cháy , không độc_hại .

Nhóm 2 . 3 : Khí độc_hại .

c ) Loại 3 . Chất_lỏng dễ cháy và chất_nổ lỏng khử nhạy ;

d ) Loại 4 ;

Nhóm 4 . 1 : Chất_rắn dễ cháy , chất tự phản_ứng và chất_nổ rắn được ngâm trong chất_lỏng hoặc bị khử nhạy .

Nhóm 4 . 2 : Chất có khả_năng tự bốc cháy .

Nhóm 4 . 3 : Chất khi tiếp_xúc với nước tạo ra khí dễ cháy .

đ ) Loại 5 ;

Nhóm 5 . 1 : Chất ô xi hoá .

Nhóm 5 . 2 : Perôxít hữu_cơ .

e ) Loại 6 ;

Nhóm 6 . 1 : Chất_độc .

Nhóm 6 . 2 : Chất gây nhiễm_bệnh .

g ) Loại 7 : Chất phóng_xạ ;

h ) Loại 8 : Chất ăn_mòn ;

i ) Loại 9 : Chất và vật_phẩm nguy_hiểm khác .

2 . Các bao_bì , thùng chứa hàng_hoá nguy_hiểm chưa được làm sạch bên trong và bên ngoài sau khi dỡ hết hàng_hoá nguy_hiểm cũng được coi là hàng_hoá nguy_hiểm tương_ứng .

Điều 5 . Danh_mục hàng_hoá nguy_hiểm

1 . Danh_mục hàng_hoá nguy_hiểm được phân theo loại , nhóm kèm theo mã_số Liên_hợp quốc và số_hiệu nguy_hiểm quy_định tại Phụ_lục I của Nghị_định này .

2 . Mức_độ nguy_hiểm của mỗi chất trong danh_mục hàng_hoá nguy_hiểm được biểu_thị bằng số_hiệu nguy_hiểm với một nhóm có 2 đến 3 chữ_số quy_định tại Phụ_lục Ii của Nghị_định này .

Điều 6 . Bao_bì , thùng chứa , đóng_gói hàng_hoá nguy_hiểm

1 . Bao_bì , thùng chứa và việc đóng_gói hàng_hoá nguy_hiểm trong lãnh_thổ Việt_nam phải tuân_thủ theo quy_chuẩn kĩ_thuật quốc_gia ( qcvn ) hoặc tiêu_chuẩn quốc_gia ( tcvn ) hoặc quy_định của pháp_luật chuyên_ngành tương_ứng với loại hàng_hoá . Bao_bì , thùng chứa đối_với hàng_hoá nhập_khẩu thực_hiện theo khuyến_cáo và yêu_cầu của nhà sản_xuất .

2 . Trường_hợp chưa có tiêu_chuẩn quốc_gia , quy_chuẩn kĩ_thuật quốc_gia hoặc quy_định của pháp_luật chuyên_ngành hoặc tiêu_chuẩn , quy_chuẩn kĩ_thuật của quốc_tế do Bộ quản_lí danh_mục hàng_hoá nguy_hiểm công_bố thì phải đáp_ứng các yêu_cầu tối_thiểu sau :

a ) Chất_lượng bao_bì , thùng chứa có_thể chịu được va_chạm và chấn_động trong quá_trình vận_chuyển , chuyển_tiếp hàng_hoá giữa các phương_tiện và xếp_dỡ vào kho ;

b ) Bao_bì , thùng chứa phải bảo_đảm không làm rò_rỉ chất nguy_hiểm trong quá_trình vận_chuyển hoặc khi vận_chuyển với các tác_động như rung lắc , thay_đổi nhiệt_độ , độ_ẩm và áp_suất ;

c ) Phía bên ngoài bao_bì , thùng chứa phải bảo_đảm sạch và không dính một loại hoá_chất nguy_hiểm nào ;

d ) Các phần của bao_bì , thùng chứa có tiếp_xúc với chất nguy_hiểm phải bảo_đảm yêu_cầu không bị ảnh_hưởng hay bị suy_giảm chất_lượng do tác_động của chất nguy_hiểm đóng bên trong ; không làm ảnh_hưởng đến thành_phần , tính_năng và tác_dụng của hàng nguy_hiểm ;

đ ) Bao_bì , thùng chứa hàng nguy_hiểm ở dạng lỏng phải bảo_đảm không bị rò_rỉ hay biến_dạng vì sự tăng thể_tích của các chất_lỏng khi thay_đổi nhiệt_độ ; có sức chịu_đựng thích_hợp với áp_suất từ phía bên trong sinh ra trong quá_trình vận_chuyển ; được thử độ rò_rỉ trước khi xuất_xưởng ;

e ) Bao_bì , thùng chứa bên trong thuộc dạng dễ bị vỡ hoặc đâm thủng như thuỷ_tinh , sành_sứ hoặc một_số loại nhựa phải được chèn cố_định với lớp bao_bì , thùng chứa bên ngoài bằng các loại vật_liệu chèn , đệm giảm_chấn_động thích_hợp ;

g ) Bao_bì , thùng chứa các chất dễ bay_hơi phải bảo_đảm giữ chất không bị bay_hơi trong quá_trình vận_chuyển theo yêu_cầu của nhà sản_xuất ;

h ) Bao_bì , thùng chứa hàng nguy_hiểm ở dạng hạt hay bột phải đảm_bảo không bị rơi_vãi trong quá_trình xếp_dỡ , vận_chuyển .

Điều 7 . Nhãn hàng , biểu_trưng nguy_hiểm và báo_hiệu nguy_hiểm

1 . Việc ghi nhãn hàng_hoá nguy_hiểm được thực_hiện theo quy_định của Luật Hoá_chất và quy_định của pháp_luật về nhãn hàng_hoá .

2 . Phía ngoài mỗi bao_bì , thùng chứa hàng_hoá nguy_hiểm có dán biểu_trưng nguy_hiểm , báo_hiệu nguy_hiểm ở vị_trí dễ quan_sát . Kích_thước , kí_hiệu , màu_sắc biểu_trưng nguy_hiểm theo mẫu quy_định tại Phụ_lục Iii của Nghị_định này .

3 . Báo_hiệu nguy_hiểm hình chữ_nhật , kích_thước và màu_sắc theo mẫu quy_định tại Phụ_lục Iii của Nghị_định này . Vị_trí dán báo_hiệu nguy_hiểm ở bên dưới biểu_trưng nguy_hiểm .

Điều 8 . Huấn_luyện an_toàn hàng_hoá nguy_hiểm

1 . Tổ_chức huấn_luyện an_toàn hàng_hoá nguy_hiểm

a ) Người thuê vận_tải hoặc người vận_tải có trách_nhiệm tổ_chức huấn_luyện an_toàn hàng_hoá nguy_hiểm hoặc cử các đối_tượng được quy_định tại khoản 2 Điều này tham_gia khoá huấn_luyện của các đơn_vị có chức_năng huấn_luyện an_toàn hàng_hoá nguy_hiểm , định_kì 02 năm một lần ;

b ) Hoạt_động huấn_luyện an_toàn hàng_hoá nguy_hiểm được tổ_chức riêng hoặc kết_hợp với hoạt_động huấn_luyện an_toàn khác ;

c ) Người đã được huấn_luyện an_toàn hàng_hoá nguy_hiểm phải được huấn_luyện lại trong các trường_hợp sau đây : Khi có sự thay_đổi chủng_loại hàng_hoá nguy_hiểm trong quá_trình vận_chuyển ; khi người đã được huấn_luyện thay_đổi vị_trí làm_việc ; sau 02 lần kiểm_tra người đã được huấn_luyện không đạt yêu_cầu ; khi hết thời_hạn 02 năm từ kể từ lần được huấn_luyện trước .

2 . Đối_tượng phải được huấn_luyện an_toàn hàng_hoá nguy_hiểm gồm : Người điều_khiển phương_tiện , người áp_tải , người thủ_kho , người xếp_dỡ .

3 . Nội_dung huấn_luyện an_toàn hàng_hoá nguy_hiểm

a ) Nội_dung huấn_luyện an_toàn hàng_hoá nguy_hiểm phải phù_hợp với vị_trí , trách_nhiệm của người được huấn_luyện ; tính_chất , chủng_loại , mức_độ nguy_hiểm của các loại hàng_hoá nguy_hiểm . Tài_liệu huấn_luyện do người thuê vận_tải hoặc người vận_tải thực_hiện , nội_dung tài_liệu được biên_soạn theo loại và nhóm loại quy_định tại Điều 4 của Nghị_định này ;

b ) Nội_dung huấn_luyện gồm : Tên hàng nguy_hiểm , tính_chất nguy_hiểm , phân_loại và ghi nhãn ; các nguy_cơ gây mất an_toàn trong quá_trình bảo_quản , xếp_dỡ , vận_chuyển hàng nguy_hiểm ; quy_trình bảo_quản , xếp_dỡ , vận_chuyển phù_hợp với vị_trí làm_việc ; quy_định về an_toàn hàng_hoá nguy_hiểm ; các quy_trình ứng_phó sự_cố : Sử_dụng các phương_tiện cứu_hộ xử_lí_sự_cố cháy , nổ , rò_rỉ , phát_tán chất nguy_hiểm , sơ_cứu người bị nạn trong sự_cố , sử_dụng , bảo_quản , kiểm_tra trang thiết_bị an_toàn , phương_tiện , trang thiết_bị bảo_vệ cá_nhân để ứng_phó sự_cố , quy_trình , sơ_đồ liên_lạc thông_báo sự_cố , phối_hợp với cơ_quan có thẩm_quyền để huy_động nguồn_lực để ứng_phó , khắc_phục sự_cố , ngăn_chặn , hạn_chế nguồn gây ô_nhiễm lan rộng ra môi_trường , thu_gom chất nguy_hiểm bị tràn đổ , khắc_phục môi_trường sau sự_cố .

4 . Người huấn_luyện an_toàn hàng_hoá nguy_hiểm phải có trình_độ đại_học trở lên và có ít_nhất 05 năm kinh_nghiệm công_tác phù_hợp với chuyên_ngành tập_huấn .

5 . Thời_gian huấn_luyện an_toàn hàng_hoá nguy_hiểm : Tối_thiểu 16 giờ cho mỗi loại và nhóm hàng nguy_hiểm , bao_gồm cả thời_gian kiểm_tra .

6 . Đánh_giá kết_quả và lưu_giữ hồ_sơ huấn_luyện an_toàn hàng_hoá nguy_hiểm

a ) Người thuê vận_tải hoặc người vận_tải hoặc đơn_vị có chức_năng huấn_luyện an_toàn hàng_hoá nguy_hiểm_chịu trách_nhiệm kiểm_tra để đánh_giá kết_quả huấn_luyện an_toàn hàng_hoá nguy_hiểm ;

b ) Kiểm_tra nội_dung huấn_luyện : Nội_dung kiểm_tra phải phù_hợp với nội_dung huấn_luyện . Thời_gian kiểm_tra tối_đa là 02 giờ . Bài kiểm_tra đạt yêu_cầu phải đạt điểm trung_bình trở lên ;

c ) Trong thời_gian 07 ngày làm_việc kể từ khi kết_thúc huấn_luyện và kiểm_tra kết_quả huấn_luyện an_toàn hàng_hoá nguy_hiểm , tổ_chức , cá_nhân tổ_chức huấn_luyện , kiểm_tra ban_hành_quyết_định công_nhận kết_quả kiểm_tra và cấp giấy chứng_nhận đã hoàn_thành huấn_luyện an_toàn hàng_hoá nguy_hiểm .

7 . Hồ_sơ huấn_luyện an_toàn hàng_hoá nguy_hiểm gồm : Nội_dung huấn_luyện ; danh_sách người được huấn_luyện với các thông_tin : Họ tên , ngày_tháng năm sinh , chức_danh , vị_trí làm_việc , chữ_kí xác_nhận tham_gia huấn_luyện ; thông_tin về người huấn_luyện bao_gồm : Họ tên , ngày_tháng năm sinh , trình_độ học_vấn , chuyên_ngành được đào_tạo , kinh_nghiệm công_tác , kèm theo các tài_liệu chứng_minh ; nội_dung và kết_quả kiểm_tra huấn_luyện an_toàn hàng_hoá nguy_hiểm ; Quyết_định công_nhận kết_quả kiểm_tra huấn_luyện an_toàn hàng_hoá nguy_hiểm của tổ_chức , cá_nhân .

8 . Tổ_chức , cá_nhân có trách_nhiệm lưu_giữ đầy_đủ hồ_sơ quy_định tại khoản 7 Điều này trong thời_gian 03 năm và xuất_trình khi cơ_quan quản_lí nhà_nước yêu_cầu .

Chương_iii

Vận_chuyển Hàng_hóa_nguy_hiểm

Mục 1 . Vận_chuyển Hàng_hóa_nguy_hiểm_bằng Phương_tiện Giao_thông Cơ_giới Đường_bộ

Điều 9 . Điều_kiện đối_với người tham_gia vận_chuyển hàng_hoá nguy_hiểm

1 . Người điều_khiển phương_tiện vận_chuyển hàng_hoá nguy_hiểm phải đảm_bảo có đủ các điều_kiện điều_khiển phương_tiện và được huấn_luyện , cấp giấy chứng_nhận đã hoàn_thành chương_trình huấn_luyện an_toàn hàng_hoá nguy_hiểm theo quy_định tại Nghị_định này .

2 . Người áp_tải , người thủ_kho , người xếp_dỡ hàng_hoá nguy_hiểm phải được huấn_luyện an_toàn và cấp giấy chứng_nhận đã hoàn_thành chương_trình huấn_luyện an_toàn về loại hàng_hoá nguy_hiểm do mình áp_tải , xếp , dỡ hoặc lưu kho .

Điều 10 . Điều_kiện đối_với phương_tiện vận_chuyển hàng_hoá nguy_hiểm

1 . Phương_tiện vận_chuyển phải đủ điều_kiện tham_gia giao_thông theo quy_định của pháp_luật . Thiết_bị chuyên_dùng của phương_tiện vận_chuyển hàng_hoá nguy_hiểm phải bảo_đảm tiêu_chuẩn quốc_gia hoặc quy_chuẩn kĩ_thuật quốc_gia hoặc theo quy_định của Bộ quản_lí chuyên_ngành .

2 . Phương_tiện vận_chuyển hàng_hoá nguy_hiểm phải dán biểu_trưng hàng_hoá nguy_hiểm . Nếu trên một phương_tiện có nhiều loại hàng_hoá nguy_hiểm khác nhau thì phương_tiện phải dán đủ biểu_trưng của các loại hàng_hoá đó . Vị_trí dán biểu_trưng ở hai bên , phía trước và phía sau của phương_tiện đảm_bảo dễ quan_sát , nhận_biết .

3 . Phương_tiện vận_chuyển hàng_hoá nguy_hiểm , sau khi dỡ hết hàng_hoá nguy_hiểm nếu không tiếp_tục vận_tải loại hàng_hoá đó thì phải được làm sạch và bóc hoặc xoá biểu_trưng nguy_hiểm trên phương_tiện vận_chuyển hàng_hoá nguy_hiểm . Đơn_vị vận_tải , người điều_khiển phương_tiện có trách_nhiệm làm sạch và bóc hoặc xoá biểu_trưng nguy_hiểm trên phương_tiện khi không tiếp_tục vận_chuyển_loại hàng_hoá nguy_hiểm đó .

Điều 11 . Xếp , dỡ hàng_hoá nguy_hiểm trên phương_tiện và lưu kho_bãi

1 . Tổ_chức , cá_nhân liên_quan đến việc xếp , dỡ hàng_hoá nguy_hiểm trên phương_tiện vận_chuyển và lưu kho , bãi phải tuân_thủ đúng chỉ_dẫn về bảo_quản , xếp , dỡ , vận_chuyển của từng loại hàng_hoá nguy_hiểm hoặc trong thông_báo của người thuê vận_tải .

2 . Việc xếp , dỡ hàng_hoá nguy_hiểm phải do người thủ_kho , người thuê vận_tải hoặc người áp_tải trực_tiếp hướng_dẫn và giám_sát . Không xếp chung các loại hàng_hoá có_thể tác_động lẫn nhau làm tăng mức_độ nguy_hiểm trong cùng một phương_tiện . Đối_với loại , nhóm hàng_hoá nguy_hiểm quy_định phải xếp , dỡ , lưu_giữ ở nơi riêng_biệt thì việc xếp , dỡ phải thực_hiện_tại khu_vực kho , bến_bãi riêng_biệt .

3 . Trường_hợp vận_chuyển hàng_hoá nguy_hiểm không quy_định phải có người áp_tải thì người vận_tải phải thực_hiện xếp , dỡ hàng_hoá theo chỉ_dẫn của người thuê vận_tải .

4 . Sau khi đưa hết hàng_hoá nguy_hiểm ra khỏi kho , bãi thì nơi lưu_giữ hàng_hoá nguy_hiểm phải được làm sạch để không ảnh_hưởng tới hàng_hoá khác .

Điều 12 . Vận_chuyển hàng_hoá nguy_hiểm là các chất dễ cháy , nổ qua công_trình hầm , phà

1 . Không được vận_chuyển các loại thuốc_nổ , khí_đốt , xăng , dầu và các chất dễ cháy , nổ , chất_rắn khử nhạy khác đi qua các công_trình hầm có chiều dài từ 100m trở lên .

2 . Không được vận_chuyển đồng_thời người ( người tham_gia giao_thông hoặc hành_khách ) cùng phương_tiện ( đã được cấp phép vận_chuyển hàng_hoá nguy_hiểm ) đang thực_hiện vận_chuyển các loại thuốc_nổ , khí ga , xăng , dầu và các chất dễ cháy , nổ khác trên cùng một chuyến phà .

Mục 2 . Vận_chuyển Hàng_hóa_nguy_hiểm Trên Đường Thủy_nội_địa

Điều 13 . Điều_kiện đối_với người tham_gia vận_chuyển hàng_hoá nguy_hiểm

1 . Thuyền_viên , người lái phương_tiện thuỷ nội_địa làm_việc trên phương_tiện vận_chuyển hàng_hoá nguy_hiểm phải được đào_tạo và có chứng_chỉ chuyên_môn đặc_biệt về vận_tải hàng_hoá nguy_hiểm theo quy_định của Bộ_trưởng Bộ Giao_thông vận_tải ; được huấn_luyện , cấp giấy chứng_nhận đã hoàn_thành chương_trình huấn_luyện an_toàn hàng_hoá nguy_hiểm theo quy_định tại Nghị_định này .

2 . Người áp_tải , người thủ_kho , người xếp_dỡ hàng_hoá nguy_hiểm trên phương_tiện và tại cảng , bến thuỷ nội_địa phải được huấn_luyện , cấp giấy chứng_nhận đã hoàn_thành chương_trình huấn_luyện an_toàn hàng_hoá nguy_hiểm do mình áp_tải , xếp , dỡ hoặc lưu kho .

Điều 14 . Điều_kiện đối_với phương_tiện vận_chuyển hàng_hoá nguy_hiểm

1 . Phương_tiện vận_chuyển phải đủ điều_kiện tham_gia giao_thông theo quy_định của pháp_luật .

2 . Phương_tiện vận_chuyển hàng_hoá nguy_hiểm phải dán biểu_trưng hàng_hoá nguy_hiểm . Nếu trên một phương_tiện có nhiều loại hàng_hoá nguy_hiểm khác nhau thì phương_tiện phải dán đủ biểu_trưng của các loại hàng_hoá đó . Vị_trí dán biểu_trưng ở hai bên của phương_tiện .

3 . Phương_tiện vận_chuyển hàng_hoá nguy_hiểm , sau khi dỡ hết hàng_hoá nguy_hiểm nếu không tiếp_tục vận_tải loại hàng_hoá đó thì phải được làm sạch và bóc hoặc xoá biểu_trưng nguy_hiểm trên phương_tiện vận_chuyển hàng_hoá nguy_hiểm . Đơn_vị vận_tải , thuyền_viên hoặc người lái phương_tiện thuỷ nội_địa có trách_nhiệm làm sạch và bóc hoặc xoá biểu_trưng nguy_hiểm trên phương_tiện khi không tiếp_tục vận_chuyển_loại hàng_hoá nguy_hiểm đó .

Điều 15 . Xếp , dỡ hàng_hoá nguy_hiểm trên phương_tiện và lưu kho_bãi

Người xếp , dỡ hàng_hoá nguy_hiểm phải thực_hiện theo quy_định về xếp_hàng_hoá trên phương_tiện thuỷ nội_địa và các quy_định sau :

1 . Việc xếp , dỡ hàng_hoá nguy_hiểm phải do người thủ_kho , người thuê vận_tải hoặc người áp_tải trực_tiếp hướng_dẫn và giám_sát ; thuyền_trưởng Quyết_định sơ_đồ xếp_hàng_hoá nguy_hiểm trên phương_tiện và việc chèn lót , chằng buộc phù_hợp tính_chất của từng loại , nhóm hàng_hoá nguy_hiểm . Không xếp chung các loại hàng_hoá có_thể tác_động lẫn nhau làm tăng mức_độ nguy_hiểm trong cùng một khoang hoặc một hầm hàng của phương_tiện .

2 . Trường_hợp vận_chuyển hàng_hoá nguy_hiểm không quy_định phải có người áp_tải thì người vận_tải phải thực_hiện xếp , dỡ hàng_hoá theo chỉ_dẫn của người thuê vận_tải .

3 . Đối_với loại , nhóm hàng_hoá nguy_hiểm quy_định phải xếp , dỡ , lưu_giữ ở nơi riêng_biệt thì việc xếp , dỡ phải thực_hiện_tại khu_vực cầu_cảng , bến , kho riêng_biệt .

4 . Sau khi đưa hết hàng_hoá nguy_hiểm ra khỏi kho , bãi thì nơi lưu_giữ hàng_hoá nguy_hiểm phải được làm sạch để không ảnh_hưởng tới hàng_hoá khác .

Chương_iv

Giấy_phép Vận_chuyển Hàng_hóa_nguy_hiểm

Điều 16 . Nội_dung , mẫu Giấy_phép và thời_hạn Giấy_phép vận_chuyển hàng_hoá nguy_hiểm

1 . Nội_dung của Giấy_phép vận_chuyển hàng_hoá nguy_hiểm

a ) Tên , địa_chỉ , điện_thoại liên_hệ của đơn_vị được cấp giấy_phép ; họ và tên , chức_danh người đại_diện theo pháp_luật ;

b ) Loại , nhóm hàng_hoá nguy_hiểm ;

c ) Hành_trình , lịch_trình vận_chuyển ( áp_dụng đối_với trường_hợp cấp theo chuyến ) ;

d ) Thời_hạn của giấy_phép .

Đối_với trường_hợp cấp theo từng chuyến hàng phải có thêm thông_tin về phương_tiện và người điều_khiển phương_tiện , người áp_tải ( áp_dụng đối_với trường_hợp vận_chuyển hàng_hoá nguy_hiểm quy_định phải có người áp_tải ) .

2 . Mẫu Giấy_phép vận_chuyển hàng_hoá nguy_hiểm phải có mã nhận_diện Qr , báo_hiệu nguy_hiểm do cơ_quan cấp quản_lí và phát_hành .

3 . Giấy_phép vận_chuyển hàng_hoá nguy_hiểm có hiệu_lực trên toàn_quốc . Thời_hạn của giấy_phép theo đề_nghị của người vận_tải nhưng tối_đa không quá 24 tháng và không quá niên_hạn sử_dụng của phương_tiện .

Điều 17 . Thẩm_quyền cấp Giấy_phép và các trường_hợp miễn cấp Giấy_phép vận_chuyển hàng_hoá nguy_hiểm

1 . Bộ Công_an tổ_chức cấp Giấy_phép vận_chuyển hàng_hoá nguy_hiểm loại 1 , loại 2 , loại 3 , loại 4 , loại 9 theo quy_định tại khoản 1 Điều 4 của Nghị_định này ( trừ hoá_chất bảo_vệ thực_vật và quy_định tại khoản 2 Điều này ) .

2 . Bộ Quốc_phòng tổ_chức cấp Giấy_phép vận_chuyển hàng_hoá nguy_hiểm cho các tổ_chức , doanh_nghiệp thuộc phạm_vi quản_lí của Bộ Quốc_phòng .

3 . Bộ Khoa_học và Công_nghệ tổ_chức cấp Giấy_phép vận_chuyển hàng_hoá nguy_hiểm loại 5 , loại 8 theo quy_định tại khoản 1 Điều 4 của Nghị_định này .

4 . Ủy_ban nhân_dân tỉnh , thành_phố trực_thuộc trung_ương tổ_chức cấp Giấy_phép vận_chuyển hàng_hoá nguy_hiểm là hoá_chất bảo_vệ thực_vật .

5 . Cơ_quan cấp Giấy_phép vận_chuyển hàng_hoá nguy_hiểm căn_cứ vào loại , nhóm hàng_hoá nguy_hiểm theo quy_định tại khoản 1 Điều 4 của Nghị_định này để Quyết_định_tuyến đường vận_chuyển và thời_gian vận_chuyển .

6 . Việc cấp Giấy_phép vận_chuyển hàng_hoá nguy_hiểm loại 7 được thực_hiện theo quy_định tại Nghị_định về việc tiến_hành công_việc bức_xạ và hoạt_động dịch_vụ hỗ_trợ ứng_dụng năng_lượng nguyên_tử .

7 . Cơ_quan cấp Giấy_phép vận_chuyển hàng_hoá nguy_hiểm từ_chối cấp giấy_phép đối_với hoạt_động vận_chuyển hàng_hoá nguy_hiểm là các chất dễ cháy , nổ có hành_trình đi qua công_trình hầm , phà theo quy_định tại Điều 12 của Nghị_định này .

8 . Tổ_chức , cá_nhân khi vận_chuyển hàng_hoá nguy_hiểm thuộc một trong các trường_hợp sau đây được miễn cấp Giấy_phép vận_chuyển hàng_hoá nguy_hiểm theo quy_định tại Nghị_định này :

a ) Vận_chuyển hàng_hoá nguy_hiểm là khí thiên_nhiên hoá_lỏng ( lng ) và khí thiên_nhiên nén ( cng ) có tổng khối_lượng nhỏ hơn 1 . 080 ki - lô - gam ;

b ) Vận_chuyển hàng_hoá nguy_hiểm là khí dầu_mỏ hoá_lỏng ( lpg ) có tổng khối_lượng nhỏ hơn 2 . 250 ki - lô - gam ;

c ) Vận_chuyển hàng_hoá nguy_hiểm là nhiên_liệu lỏng có tổng_dung_tích nhỏ hơn 1 . 500 lít ;

d ) Vận_chuyển hàng_hoá nguy_hiểm là hoá_chất bảo_vệ thực_vật có tổng khối_lượng nhỏ hơn 1 . 000 ki - lô - gam ;

đ ) Vận_chuyển hàng_hoá nguy_hiểm đối_với các hoá_chất_độc nguy_hiểm_còn lại trong các loại , nhóm hàng_hoá nguy_hiểm .

9 . Phương_tiện vận_chuyển hàng_hoá nguy_hiểm không phải đề_nghị cấp Giấy_phép vận_chuyển hàng_hoá nguy_hiểm quy_định tại khoản 8 Điều này phải đảm_bảo các điều_kiện an_toàn phòng cháy , chữa_cháy theo quy_định pháp_luật về phòng cháy , chữa_cháy trong quá_trình vận_chuyển .

Điều 18 . Hồ_sơ đề_nghị cấp , cấp lại Giấy_phép vận_chuyển hàng_hoá nguy_hiểm

1 . Hồ_sơ đề_nghị cấp Giấy_phép vận_chuyển hàng_hoá nguy_hiểm loại 5 , loại 8 bao_gồm :

a ) Giấy đề_nghị cấp Giấy_phép vận_chuyển hàng_hoá nguy_hiểm theo mẫu quy_định tại Phụ_lục Iv của Nghị_định này ;

b ) Bản_sao hoặc bản_sao điện_tử hoặc bản_chính Bảng kê danh_sách phương_tiện tham_gia vận_chuyển đảm_bảo còn thời_hạn kiểm_định theo quy_định ;

c ) Bản_sao hoặc bản_sao điện_tử hoặc bản_chính Bảng kê danh_sách người điều_khiển phương_tiện vận_chuyển hàng_hoá nguy_hiểm ( gồm : Họ và tên ; số chứng_minh_thư nhân_dân hoặc số căn_cước công_dân hoặc số hộ_chiếu ; số giấy_phép , hạng giấy_phép ( đối_với lái_xe ) ; số giấy chứng_nhận khả_năng chuyên_môn , hạng ( đối_với thuyền_viên ) ) và danh_sách người áp_tải đối_với trường_hợp bắt_buộc phải có người áp_tải ( gồm : Họ và tên , số chứng_minh_thư nhân_dân hoặc số căn_cước công_dân hoặc số hộ_chiếu ) kèm bản_sao giấy chứng_nhận hoàn_thành chương_trình huấn_luyện an_toàn ;

d ) Bản_sao hoặc bản_sao điện_tử hoặc bản_chính phương_án tổ_chức vận_chuyển , hàng_hoá nguy_hiểm của đơn_vị vận_chuyển theo mẫu quy_định tại Phụ_lục V của Nghị_định này ( trong đó bao_gồm tối_thiểu các nội_dung : Biển kiểm_soát xe ; họ và tên người điều_khiển phương_tiện ; loại hàng ; khối_lượng ; tuyến đường , thời_gian vận_chuyển ; biện_pháp ứng_cứu sự_cố hoá_chất trong vận_chuyển hàng_hoá nguy_hiểm ) ;

đ ) Bản_sao hoặc bản_sao điện_tử Giấy chứng_nhận đã hoàn_thành chương_trình huấn_luyện an_toàn của người điều_khiển phương_tiện cơ_giới đường_bộ đối_với vận_chuyển hàng_hoá nguy_hiểm bằng phương_tiện giao_thông cơ_giới đường_bộ ; bản_sao hoặc bản_sao điện_tử chứng_chỉ chuyên_môn đặc_biệt của thuyền_viên đối_với vận_chuyển hàng_hoá nguy_hiểm trên đường_thuỷ nội_địa .

2 . Hồ_sơ_cấp Giấy_phép vận_chuyển hàng_hoá nguy_hiểm loại 1 , loại 2 , loại 3 , loại 4 và loại 9 bao_gồm :

a ) Giấy đề_nghị cấp Giấy_phép vận_chuyển hàng_hoá nguy_hiểm theo mẫu quy_định tại Phụ_lục Iv của Nghị_định này ;

b ) Bản_sao hoặc bản_sao điện_tử hoặc bản_chính Bảng kê danh_sách phương_tiện tham_gia vận_chuyển đảm_bảo còn thời_hạn kiểm_định theo quy_định ;

c ) Bản_sao hoặc bản_sao điện_tử hoặc bản_chính Bảng kê danh_sách người điều_khiển phương_tiện vận_chuyển hàng_hoá nguy_hiểm ( gồm : Họ và tên ; số chứng_minh_thư nhân_dân hoặc số căn_cước công_dân hoặc số hộ_chiếu ; số giấy_phép , hạng giấy_phép ( đối_với lái_xe ) ; số giấy chứng_nhận khả_năng chuyên_môn , hạng ( đối_với thuyền_viên ) ) và danh_sách người áp_tải đối_với trường_hợp bắt_buộc phải có người áp_tải ( gồm : Họ và tên , số chứng_minh_thư nhân_dân hoặc số căn_cước công_dân hoặc số hộ_chiếu ) kèm bản_sao giấy chứng_nhận hoàn_thành chương_trình huấn_luyện an_toàn theo quy_định ;

d ) Bản_sao hoặc bản_sao điện_tử Giấy chứng_nhận đã hoàn_thành chương_trình huấn_luyện của người điều_khiển phương_tiện cơ_giới đường_bộ đối_với vận_chuyển hàng_hoá nguy_hiểm bằng phương_tiện giao_thông cơ_giới đường_bộ ; bản_sao hoặc bản_sao điện_tử chứng_chỉ chuyên_môn đặc_biệt của thuyền_viên đối_với vận_chuyển hàng_hoá nguy_hiểm trên đường_thuỷ nội_địa ;

đ ) Bản_sao hoặc bản_sao điện_tử hoặc bản_chính phương_án tổ_chức vận_chuyển hàng_hoá nguy_hiểm của đơn_vị vận_chuyển theo mẫu quy_định tại Phụ_lục V của Nghị_định này ( trong đó bao_gồm tối_thiểu các nội_dung : Biển kiểm_soát xe ; họ và tên người điều_khiển phương_tiện ; loại hàng ; khối_lượng ; tuyến đường , thời_gian vận_chuyển ; biện_pháp ứng_cứu khẩn_cấp khi có sự_cố cháy , nổ ) ; bản_sao hoặc bản_sao điện_tử hoặc bản_chính Phương_án ứng_phó sự_cố tràn dầu ( chỉ áp_dụng đối_với trường_hợp vận_tải xăng dầu trên đường_thuỷ nội_địa ) .

3 . Hồ_sơ_cấp Giấy_phép vận_chuyển hàng_hoá nguy_hiểm là hoá_chất bảo_vệ thực_vật bao_gồm :

a ) Giấy đề_nghị cấp Giấy_phép vận_chuyển hàng_hoá nguy_hiểm theo mẫu quy_định tại Phụ_lục Iv của Nghị_định này ;

b ) Bản_sao hoặc bản_sao điện_tử hoặc bản_chính Bảng kê danh_sách phương_tiện tham_gia vận_chuyển đảm_bảo còn thời_hạn kiểm_định theo quy_định ;

c ) Bản_sao hoặc bản_sao điện_tử hoặc bản_chính Bảng kê danh_sách người điều_khiển phương_tiện vận_chuyển hàng_hoá nguy_hiểm ( gồm : Họ và tên ; số chứng_minh_thư nhân_dân hoặc số căn_cước công_dân hoặc số hộ_chiếu ; số giấy_phép , hạng giấy_phép ( đối_với lái_xe ) ; số giấy chứng_nhận khả_năng chuyên_môn , hạng ( đối_với thuyền_viên ) ) và danh_sách người áp_tải đối_với trường_hợp bắt_buộc phải có người áp_tải ( gồm : Họ và tên , số chứng_minh_thư nhân_dân hoặc số căn_cước công_dân hoặc số hộ_chiếu ) kèm bản_sao giấy chứng_nhận hoàn_thành chương_trình huấn_luyện an_toàn theo quy_định ;

d ) Bản_sao hoặc bản_sao điện_tử hoặc bản_chính một trong các giấy_tờ sau : Hợp_đồng cung_ứng ; Hoá_đơn tài_chính về xuất , nhập hàng_hoá thuốc bảo_vệ thực_vật ;

đ ) Bản_sao hoặc bản_sao điện_tử hoặc bản_chính phương_án tổ_chức vận_chuyển hàng_hoá nguy_hiểm của đơn_vị vận_chuyển theo mẫu quy_định tại Phụ_lục V của Nghị_định này ( trong đó bao_gồm tối_thiểu các nội_dung : Biển kiểm_soát xe ; họ và tên người điều_khiển phương_tiện ; loại hàng ; khối_lượng ; tuyến đường , thời_gian vận_chuyển ) ;

e ) Bản_sao hoặc bản_sao điện_tử Giấy chứng_nhận đã hoàn_thành chương_trình huấn_luyện an_toàn của người điều_khiển phương_tiện cơ_giới đường_bộ đối_với vận_chuyển hàng_hoá nguy_hiểm bằng phương_tiện giao_thông cơ_giới đường_bộ ; bản_sao hoặc bản_sao điện_tử chứng_chỉ chuyên_môn đặc_biệt của thuyền_viên đối_với vận_chuyển hàng_hoá nguy_hiểm trên đường_thuỷ nội_địa .

4 . Hồ_sơ đề_nghị điều_chỉnh thông_tin trên Giấy_phép khi có sự thay_đổi liên_quan đến nội_dung của Giấy_phép bao_gồm :

a ) Giấy đề_nghị điều_chỉnh thông_tin trên Giấy_phép vận_chuyển hàng_hoá nguy_hiểm theo mẫu quy_định tại Phụ_lục IVa của Nghị_định này ;

b ) Hồ_sơ chứng_minh sự thay_đổi về thông_tin liên_quan đến giấy_phép .

5 . Hồ_sơ_cấp lại Giấy_phép do bị mất , bị hỏng bao_gồm : Giấy đề_nghị cấp lại Giấy_phép vận_chuyển hàng_hoá nguy_hiểm ( trong đó nêu lí_do : bị mất hoặc bị hỏng ) .

Điều 19 . Trình_tự , thủ_tục cấp , cấp lại Giấy_phép vận_chuyển hàng_hoá nguy_hiểm

1 . Thủ_tục cấp Giấy_phép vận_chuyển hàng_hoá nguy_hiểm

a ) Người vận_tải hàng_hoá nguy_hiểm_nộp 01 bộ hồ_sơ đề_nghị cấp Giấy_phép vận_chuyển hàng_hoá nguy_hiểm theo quy_định tại khoản 1 , khoản 2 , khoản 3 Điều 18 của Nghị_định này đến cơ_quan cấp Giấy_phép vận_chuyển hàng_hoá nguy_hiểm .

Trường_hợp nộp hồ_sơ trực_tiếp : Cơ_quan giải_quyết thủ_tục hành_chính kiểm_tra thành_phần hồ_sơ và trả_lời ngay khi tổ_chức , cá_nhân đến nộp hồ_sơ ; trường_hợp_thành_phần hồ_sơ chưa đầy_đủ hoặc có sai_lệch thì hướng_dẫn hoàn_thiện hồ_sơ theo quy_định .

Trường_hợp nộp hồ_sơ qua dịch_vụ bưu_chính hoặc qua hệ_thống dịch_vụ công trực_tuyến : Trong thời_hạn không quá 01 ngày làm_việc kể từ ngày nhận hồ_sơ , cơ_quan giải_quyết thủ_tục hành_chính xem_xét tính đầy_đủ , nếu hồ_sơ chưa đầy_đủ theo quy_định , cơ_quan giải_quyết thủ_tục hành_chính thông_báo bằng văn_bản hoặc thông_qua hệ_thống dịch_vụ công trực_tuyến cho tổ_chức , cá_nhân biết để bổ_sung , đồng_thời hướng_dẫn hoàn_thiện hồ_sơ theo quy_định .

Riêng đối_với thủ_tục cấp Giấy_phép vận_chuyển hàng_hoá nguy_hiểm loại 7 thực_hiện theo quy_định về việc tiến_hành công_việc bức_xạ và hoạt_động dịch_vụ hỗ_trợ ứng_dụng năng_lượng nguyên_tử ;

b ) Trong thời_hạn 05 ngày làm_việc , kể từ ngày nhận đủ hồ_sơ đúng theo quy_định , cơ_quan cấp Giấy_phép thẩm_định hồ_sơ_cấp Giấy_phép vận_chuyển hàng_hoá nguy_hiểm . Trường_hợp không cấp Giấy_phép thì cơ_quan cấp Giấy_phép phải trả_lời bằng văn_bản hoặc thông_báo qua hệ_thống dịch_vụ công trực_tuyến và nêu rõ lí_do .

2 . Thủ_tục điều_chỉnh thông_tin trên Giấy_phép vận_chuyển hàng_hoá nguy_hiểm khi có sự thay_đổi liên_quan đến nội_dung của Giấy_phép

a ) Người vận_tải vận_chuyển hàng_hoá nguy_hiểm_nộp 01 bộ hồ_sơ đề_nghị cấp Giấy_phép vận_chuyển hàng_hoá nguy_hiểm theo quy_định tại khoản 4 Điều 18 của Nghị_định này đến cơ_quan cấp Giấy_phép .

Trường_hợp nộp hồ_sơ trực_tiếp : Cơ_quan giải_quyết thủ_tục hành_chính kiểm_tra thành_phần hồ_sơ và trả_lời ngay khi tổ_chức , cá_nhân đến nộp hồ_sơ ; trường_hợp_thành_phần hồ_sơ chưa đầy_đủ hoặc có sai_lệch thì hướng_dẫn hoàn_thiện hồ_sơ theo quy_định .

Trường_hợp nộp hồ_sơ qua dịch_vụ bưu_chính hoặc qua hệ_thống dịch_vụ công trực_tuyến : Trong thời_hạn không quá 01 ngày làm_việc kể từ ngày nhận hồ_sơ , cơ_quan giải_quyết thủ_tục hành_chính xem_xét tính đầy_đủ , nếu hồ_sơ chưa đầy_đủ theo quy_định , cơ_quan giải_quyết thủ_tục hành_chính thông_báo bằng văn_bản hoặc thông_qua hệ_thống dịch_vụ công trực_tuyến cho tổ_chức , cá_nhân biết để bổ_sung , đồng_thời hướng_dẫn hoàn_thiện hồ_sơ theo quy_định .

b ) Trong thời_hạn 03 ngày làm_việc , kể từ ngày nhận đủ hồ_sơ đúng theo quy_định , cơ_quan cấp Giấy_phép thẩm_định hồ_sơ , ban_hành_văn_bản điều_chỉnh nội_dung Giấy_phép vận_chuyển hàng_hoá nguy_hiểm . Trường_hợp không đồng_ý , cơ_quan cấp Giấy_phép phải trả_lời bằng văn_bản hoặc thông_báo qua hệ_thống dịch_vụ công trực_tuyến và nêu rõ lí_do .

3 . Thủ_tục cấp lại Giấy_phép vận_chuyển hàng_hoá nguy_hiểm do bị mất , bị hỏng

a ) Người vận_tải vận_chuyển hàng_hoá nguy_hiểm_nộp 01 bộ hồ_sơ đề_nghị cấp Giấy_phép vận_chuyển hàng_hoá nguy_hiểm theo quy_định tại khoản 5 Điều 18 của Nghị_định này đến cơ_quan cấp Giấy_phép .

Trường_hợp nộp hồ_sơ trực_tiếp : Cơ_quan giải_quyết thủ_tục hành_chính kiểm_tra thành_phần hồ_sơ và trả_lời ngay khi tổ_chức , cá_nhân đến nộp hồ_sơ ; trường_hợp_thành_phần hồ_sơ chưa đầy_đủ hoặc có sai_lệch thì hướng_dẫn hoàn_thiện hồ_sơ theo quy_định .

Trường_hợp nộp hồ_sơ qua dịch_vụ bưu_chính hoặc qua hệ_thống dịch_vụ công trực_tuyến : Trong thời_hạn không quá 01 ngày làm_việc kể từ ngày nhận hồ_sơ , cơ_quan giải_quyết thủ_tục hành_chính xem_xét tính đầy_đủ , nếu hồ_sơ chưa đầy_đủ theo quy_định , cơ_quan giải_quyết thủ_tục hành_chính thông_báo bằng văn_bản hoặc thông_qua hệ_thống dịch_vụ công trực_tuyến cho tổ_chức , cá_nhân biết để bổ_sung , đồng_thời hướng_dẫn hoàn_thiện hồ_sơ theo quy_định ;

b ) Trong thời_hạn 02 ngày làm_việc , kể từ ngày nhận đủ hồ_sơ đúng theo quy_định , cơ_quan cấp Giấy_phép thẩm_định hồ_sơ_cấp Giấy_phép vận_chuyển hàng_hoá nguy_hiểm . Trường_hợp không cấp Giấy_phép thì cơ_quan cấp Giấy_phép phải trả_lời bằng văn_bản hoặc thông_báo qua hệ_thống dịch_vụ công trực_tuyến và nêu rõ lí_do .

4 . Trong quá_trình hoạt_động vận_chuyển hàng_hoá nguy_hiểm , nếu có sự thay_đổi phương_tiện và người điều_khiển phương_tiện so với danh_sách trong hồ_sơ đã được cấp Giấy_phép vận_chuyển hàng_hoá nguy_hiểm thì đơn_vị vận_chuyển hàng_hoá nguy_hiểm phải thông_báo_danh_sách kèm theo hồ_sơ các phương_tiện và người điều_khiển phương_tiện thay_thế đến cơ_quan cấp giấy_phép tối_thiểu 03 ngày làm_việc trước khi thực_hiện vận_chuyển .

Trong thời_hạn 01 ngày làm_việc , kể từ ngày nhận thông_báo kèm hồ_sơ của đơn_vị vận_chuyển hàng_hoá hàng_hoá nguy_hiểm , cơ_quan cấp Giấy_phép kiểm_tra và có văn_bản thông_báo_danh_sách phương_tiện và người điều_khiển phương_tiện thay_thế . Trường_hợp không đồng_ý thì cơ_quan cấp Giấy_phép phải trả_lời bằng văn_bản hoặc thông_báo qua hệ_thống dịch_vụ công trực_tuyến và nêu rõ lí_do .

5 . Việc tiếp_nhận hồ_sơ và trả kết_quả được thực_hiện trực_tiếp tại trụ_sở cơ_quan cấp Giấy_phép hoặc qua dịch_vụ bưu_chính hoặc qua môi_trường mạng .

Điều 20 . Thu_hồi Giấy_phép vận_chuyển hàng_hoá nguy_hiểm

1 . Người vận_tải vận_chuyển hàng_hoá nguy_hiểm bị thu_hồi Giấy_phép một trong các trường_hợp sau đây :

a ) Cung_cấp bản_sao không đúng với bản_chính hoặc thông_tin sai_lệch trong hồ_sơ đề_nghị cấp Giấy vận_chuyển hàng nguy_hiểm ;

b ) Thực_hiện việc vận_chuyển hàng_hoá nguy_hiểm không đúng với hồ_sơ đề_nghị cấp giấy_phép hoặc không đúng với Giấy_phép vận_chuyển hàng_hoá nguy_hiểm đã được cấp ;

c ) Chấm_dứt hoạt_động theo quy_định của pháp_luật ;

d ) Sử_dụng người tham_gia vận_chuyển hàng_hoá nguy_hiểm khi chưa được huấn_luyện an_toàn hàng_hoá nguy_hiểm theo quy_định .

2 . Cơ_quan cấp Giấy_phép vận_chuyển hàng_hoá nguy_hiểm thu_hồi Giấy_phép do cơ_quan mình cấp và thực_hiện theo trình_tự sau đây :

a ) Ban_hành_quyết_định thu_hồi Giấy_phép ;

b ) Gửi Quyết_định thu_hồi Giấy_phép đến người vận_tải và phải đăng_tải thông_tin trên Trang thông_tin điện_tử của đơn_vị ( nếu có ) ;

c ) Khi cơ_quan cấp Giấy_phép ban_hành_quyết_định thu_hồi Giấy_phép thì người vận_tải phải nộp lại Giấy_phép cho cơ_quan cấp Giấy_phép đồng_thời dừng hoạt_động vận_chuyển hàng_hoá nguy_hiểm theo Quyết_định thu_hồi Giấy_phép ngay sau khi Quyết_định có hiệu_lực thi_hành . Trường_hợp người vận_tải vi_phạm_quy_định tại điểm a , điểm b và điểm d khoản 1 Điều này dẫn đến bị thu_hồi Giấy_phép , cơ_quan cấp Giấy_phép không cấp lại Giấy_phép trong thời_gian 30 ngày kể từ ngày Quyết_định thu_hồi có hiệu_lực thi_hành . Sau thời_gian 30 ngày kể từ ngày Quyết_định thu_hồi có hiệu_lực thi_hành , nếu có nhu_cầu tiếp_tục tham_gia vận_chuyển thì người vận_tải phải làm thủ_tục như cấp lần đầu để được cấp Giấy_phép theo quy_định tại Điều 18 của Nghị_định này ;

d ) Thông_báo trên các phương_tiện thông_tin đại_chúng , trên Cổng hoặc trang thông_tin điện_tử của cơ_quan về việc thu_hồi Giấy_phép đã cấp .

Chương V

Tổ_chức Thực_hiện

Điều 21 . Bộ Giao_thông vận_tải

1 . Chủ_trì tổng_hợp_ý_kiến của các bộ , ngành có liên_quan trong việc sửa_đổi , bổ_sung danh_mục hàng_hoá nguy_hiểm_trình Chính_phủ ban_hành ; tổng_hợp báo_cáo về vận_chuyển hàng_hoá nguy_hiểm theo quy_định tại Nghị_định này .

2 . Ban_hành quy_chuẩn kĩ_thuật quốc_gia về an_toàn kĩ_thuật và bảo_vệ môi_trường đối_với phương_tiện thuỷ nội_địa và phương_tiện giao_thông cơ_giới đường_bộ chở hàng_hoá nguy_hiểm , thiết_bị chuyên_dùng gắn cố_định ( không_thể tách rời ) trên phương_tiện vận_chuyển hàng_hoá nguy_hiểm .

3 . Phối_hợp với các bộ , ngành có liên_quan trong công_tác quản_lý , thanh_tra , kiểm_tra và xử_lí vi_phạm đối_với hoạt_động vận_chuyển hàng_hoá nguy_hiểm .

Điều 22 . Bộ Công_an

1 . Quản_lí danh_mục hàng_hoá nguy_hiểm loại 1 và loại 4 trong phạm_vi quản_lý ; quản_lí hoạt_động vận_chuyển hàng_hoá nguy_hiểm và tổ_chức thực_hiện việc cấp Giấy_phép vận_chuyển hàng_hoá nguy_hiểm theo quy_định tại khoản 1 Điều 17 của Nghị_định này .

2 . Phối_hợp với Bộ Giao_thông vận_tải , Bộ Quốc_phòng , Bộ Công_thương , Bộ Tài_nguyên và Môi_trường tham_mưu Chính_phủ sửa_đổi , bổ_sung danh_mục hàng_hoá nguy_hiểm loại 1 , loại 4 và loại 9 theo quy_định tại khoản 1 Điều 4 của Nghị_định này .

3 . Chủ_trì , phối_hợp với các bộ , ngành có liên_quan trong công_tác quản_lý , thanh_tra , kiểm_tra và xử_lí vi_phạm đối_với hoạt_động vận_chuyển hàng_hoá nguy_hiểm theo thẩm_quyền . Thanh_tra , kiểm_tra và xử_lí vi_phạm đối_với hoạt_động huấn_luyện an_toàn hàng_hoá nguy_hiểm theo thẩm_quyền .

Điều 23 . Bộ Quốc_phòng

1 . Quản_lí hoạt_động vận_chuyển hàng_hoá nguy_hiểm và tổ_chức thực_hiện việc cấp Giấy_phép vận_chuyển hàng_hoá nguy_hiểm trong phạm_vi quản_lí theo quy_định tại khoản 2 Điều 17 của Nghị_định này .

2 . Thực_hiện công_tác kiểm_tra , kiểm_soát xuất nhập_cảnh và phối_hợp kiểm_tra , giám_sát hàng_hoá nguy_hiểm , phương_tiện vận_chuyển hàng_hoá nguy_hiểm bằng phương_tiện giao_thông cơ_giới đường_bộ và vận_chuyển hàng_hoá nguy_hiểm trên đường_thuỷ nội_địa trong khu_vực biên_giới , cửa_khẩu biên_giới đất_liền , cửa_khẩu cảng theo quy_định của pháp_luật ; bố_trí làn dành riêng cho phương_tiện chuyên_chở hàng_hoá nguy_hiểm lưu_thông tại cửa_khẩu biên_giới đất_liền có nhiều phương_tiện vận_chuyển hàng nguy_hiểm hoạt_động .

Điều 24 . Bộ Khoa_học và Công_nghệ

1 . Quản_lí hoạt_động vận_chuyển hàng_hoá nguy_hiểm , danh_mục hàng_hoá nguy_hiểm và tổ_chức thực_hiện việc cấp Giấy_phép vận_chuyển hàng_hoá nguy_hiểm trong phạm_vi quản_lí theo quy_định tại khoản 3 Điều 17 của Nghị_định này .

2 . Chủ_trì , phối_hợp với Bộ Giao_thông vận_tải và Bộ Công_thương tham_mưu Chính_phủ sửa_đổi , bổ_sung Danh_mục hàng_hoá nguy_hiểm loại 5 , loại 7 , loại 8 theo quy_định tại khoản 1 Điều 4 Nghị_định này trình cấp có thẩm_quyền phê_duyệt công_bố áp_dụng

3 . Quy_định loại hàng_hoá nguy_hiểm thuộc loại 5 , loại 8 khi vận_chuyển bắt_buộc phải có người áp_tải .

4 . Chủ_trì , phối_hợp với các bộ , ngành liên_quan trong công_tác quản_lý , thanh_tra , kiểm_tra và xử_lí vi_phạm đối_với hoạt_động vận_chuyển hàng_hoá nguy_hiểm theo thẩm_quyền . Thanh_tra , kiểm_tra và xử_lí vi_phạm đối_với hoạt_động huấn_luyện an_toàn hàng_hoá nguy_hiểm theo thẩm_quyền .

Điều 25 . Bộ Y_tế

1 . Quản_lí danh_mục hàng_hoá nguy_hiểm đối_với các loại hoá_chất_độc dùng trong lĩnh_vực y_tế và hoá_chất diệt côn_trùng , diệt khuẩn dùng trong lĩnh_vực gia_dụng trong phạm_vi quản_lí theo quy_định tại khoản 1 Điều 4 của Nghị_định này .

2 . Chủ_trì , phối_hợp với Bộ Giao_thông vận_tải tham_mưu Chính_phủ sửa_đổi , bổ_sung danh_mục hàng_hoá nguy_hiểm liên_quan đến các loại hoá_chất_độc , chất gây nhiễm_bệnh dùng trong lĩnh_vực y_tế và hoá_chất diệt côn_trùng , diệt khuẩn dùng trong lĩnh_vực gia_dụng .

3 . Quy_định loại hàng_hoá nguy_hiểm liên_quan đến các loại hoá_chất_độc , chất gây nhiễm_bệnh dùng trong lĩnh_vực y_tế và hoá_chất diệt côn_trùng , diệt khuẩn dùng trong lĩnh_vực gia_dụng khi vận_chuyển bắt_buộc phải có người áp_tải .

4 . Phối_hợp với các bộ , ngành có liên_quan trong công_tác quản_lý , thanh_tra , kiểm_tra và xử_lí vi_phạm đối_với hoạt_động vận_chuyển hàng_hoá nguy_hiểm theo thẩm_quyền . Thanh_tra , kiểm_tra và xử_lí vi_phạm đối_với hoạt_động huấn_luyện an_toàn hàng_hoá nguy_hiểm theo thẩm_quyền .

Điều 26 . Bộ Công_thương

1 . Quản_lí danh_mục hàng_hoá nguy_hiểm đối_với loại 2 , loại 3 , loại 9 , các loại xăng dầu , khí_đốt và các hoá_chất nguy_hiểm , các hoá_chất_độc nguy_hiểm_còn lại theo quy_định tại khoản 1 Điều 4 của Nghị_định này .

2 . Chủ_trì , phối_hợp với Bộ Giao_thông vận_tải , Bộ Công_an và các bộ , ngành có liên_quan tham_mưu Chính_phủ sửa_đổi , bổ_sung danh_mục hàng_hoá nguy_hiểm loại 2 , loại 3 , loại 9 , các loại xăng dầu , khí_đốt và các hoá_chất nguy_hiểm , các hoá_chất_độc nguy_hiểm_còn lại theo quy_định tại khoản 1 Điều 4 của Nghị_định này .

3 . Phối_hợp với các bộ , ngành có liên_quan trong công_tác quản_lý , thanh_tra , kiểm_tra và xử_lí vi_phạm đối_với hoạt_động vận_chuyển hàng_hoá nguy_hiểm theo thẩm_quyền . Thanh_tra , kiểm_tra và xử_lí vi_phạm đối_với hoạt_động huấn_luyện an_toàn hàng_hoá nguy_hiểm theo thẩm_quyền .

Điều 27 . Bộ Nông_nghiệp và Phát_triển nông_thôn

1 . Quản_lí danh_mục hàng_hoá nguy_hiểm là hoá_chất bảo_vệ thực_vật .

2 . Chủ_trì , phối_hợp với Bộ Giao_thông vận_tải tham_mưu Chính_phủ sửa_đổi , bổ_sung danh_mục hàng_hoá nguy_hiểm liên_quan đến hoá_chất bảo_vệ thực_vật .

3 . Phối_hợp với các bộ , ngành có liên_quan trong công_tác quản_lý , thanh_tra , kiểm_tra và xử_lí vi_phạm đối_với hoạt_động vận_chuyển hàng_hoá nguy_hiểm theo thẩm_quyền .

Điều 28 . Bộ Tài_nguyên và Môi_trường

Phối_hợp với các bộ , ngành có liên_quan trong công_tác quản_lý , thanh_tra , kiểm_tra và xử_lí vi_phạm đối_với hoạt_động vận_chuyển hàng_hoá nguy_hiểm theo thẩm_quyền .

Điều 29 . Bộ Tài_chính

Thực_hiện công_tác kiểm_tra , giám_sát , kiểm_soát xuất nhập_cảnh ; kiểm_tra , giám_sát hàng_hoá nguy_hiểm , phương_tiện vận_chuyển hàng_hoá nguy_hiểm trong địa_bàn hoạt_động hải_quan theo quy_định của pháp_luật .

Điều 30 . Ủy_ban nhân_dân các tỉnh , thành_phố trực_thuộc trung_ương

1 . Quản_lí hoạt_động vận_chuyển hàng nguy_hiểm và tổ_chức thực_hiện cấp Giấy_phép vận_chuyển hàng_hoá nguy_hiểm là hoá_chất bảo_vệ thực_vật theo quy_định tại khoản 4 Điều 17 của Nghị_định này .

2 . Phối_hợp với các bộ , ngành có liên_quan trong công_tác quản_lý , thanh_tra , kiểm_tra và xử_lí vi_phạm đối_với hoạt_động vận_chuyển hàng_hoá nguy_hiểm theo thẩm_quyền . Thanh_tra , kiểm_tra và xử_lí vi_phạm đối_với hoạt_động huấn_luyện an_toàn hàng_hoá nguy_hiểm là hoá_chất bảo_vệ thực_vật .

3 . Chỉ_đạo Ủy_ban nhân_dân cấp huyện , xã khi xảy ra sự_cố trong quá_trình vận_chuyển hàng_hoá nguy_hiểm trên địa_bàn quản_lý , phải thực_hiện các nội_dung sau :

a ) Giúp người điều_khiển phương_tiện và người áp_tải ( nếu có ) trong việc cứu người , cứu hàng , cứu phương_tiện ;

b ) Đưa nạn_nhân ra khỏi khu_vực có sự_cố , tổ_chức cấp_cứu nạn_nhân ;

c ) Tổ_chức bảo_vệ hàng_hoá , phương_tiện để tiếp_tục vận_chuyển hoặc lưu kho , bãi , chuyển_tải theo hướng_dẫn của cơ_quan có thẩm_quyền ;

d ) Khoanh vùng , sơ_tán dân_cư ra khỏi khu_vực ảnh_hưởng nguy_hiểm , đồng_thời báo_cáo Ủy_ban nhân_dân cấp trên và cơ_quan hữu_quan khác để huy_động các lực_lượng cần_thiết đến xử_lí kịp_thời .

Điều 31 . Đối_với người thuê vận_tải

1 . Đóng_gói đúng kích_cỡ , khối_lượng hàng và chất_liệu bao_bì , thùng chứa theo tiêu_chuẩn kĩ_thuật của từng loại hàng_hoá nguy_hiểm theo quy_định .

2 . Bao_bì , thùng chứa ngoài phải có nhãn hàng_hoá , có dán biểu_trưng nguy_hiểm , báo_hiệu nguy_hiểm theo quy_định tại Điều 7 của Nghị_định này .

3 . Lập 04 bộ hồ_sơ về hàng_hoá nguy_hiểm cần vận_chuyển ( 01 bộ gửi người vận_tải hàng_hoá nguy_hiểm ; 01 bộ gửi người xếp , dỡ hàng_hoá nguy_hiểm ; 01 bộ gửi người lái_xe hoặc thuyền_trưởng hoặc người lái phương_tiện thuỷ nội_địa ; 01 bộ lưu người thuê vận_tải ) . Hồ_sơ bao_gồm : Giấy gửi hàng ghi rõ : Tên hàng_hoá nguy_hiểm , mã_số , loại nhóm hàng , khối_lượng tổng_cộng , loại bao_bì , số_lượng bao_gói , ngày sản_xuất , nơi sản_xuất ; họ và tên , địa_chỉ của người thuê vận_tải và người nhận hàng .

4 . Thông_báo bằng văn_bản cho người vận_tải về những yêu_cầu phải thực_hiện trong quá_trình vận_chuyển , hướng_dẫn xử_lí trong trường_hợp có tai_nạn , sự_cố kể_cả trong trường_hợp có người áp_tải .

5 . Tổ_chức hoặc thuê đơn_vị có chức_năng huấn_luyện an_toàn hàng_hoá nguy_hiểm đối_với người áp_tải , người xếp_dỡ , người thủ_kho theo quy_định tại Điều 8 của Nghị_định này . Cử người áp_tải nếu hàng_hoá nguy_hiểm có quy_định bắt_buộc có người áp_tải .

6 . Trang_bị đầy_đủ đồ bảo_hộ theo quy_định cho người áp_tải , người thủ_kho , người xếp_dỡ hàng_hoá nguy_hiểm .

Điều 32 . Đối_với người vận_tải

1 . Bố_trí phương_tiện vận_chuyển phù_hợp với loại hàng_hoá nguy_hiểm cần vận_chuyển .

2 . Kiểm_tra hàng_hoá bảo_đảm an_toàn trước khi thực_hiện vận_chuyển theo quy_định .

3 . Chấp_hành đầy_đủ thông_báo của người thuê vận_tải và những quy_định ghi trong Giấy_phép vận_chuyển hàng_hoá nguy_hiểm .

4 . Thực_hiện niêm_yết biểu_trưng nguy_hiểm của loại , nhóm loại hàng_hoá nguy_hiểm đang vận_chuyển theo quy_định .

5 . Phải làm sạch và bóc hoặc xoá biểu_trưng nguy_hiểm trên phương_tiện vận_chuyển hàng_hoá nguy_hiểm sau khi dỡ hết hàng nếu không tiếp_tục vận_chuyển_loại hàng đó .

6 . Chấp_hành các quy_định ghi trong Giấy_phép và chỉ được tổ_chức vận_chuyển hàng_hoá nguy_hiểm khi có Giấy_phép vận_chuyển hàng_hoá nguy_hiểm còn hiệu_lực đối_với loại , nhóm , tên hàng_hoá quy_định phải có Giấy_phép , có biểu_trưng , báo_hiệu nguy_hiểm .

7 . Chỉ_thực_hiện vận_chuyển hàng_hoá nguy_hiểm khi hàng_hoá có đầy_đủ thủ_tục , hồ_sơ hợp_lệ , đóng_gói bảo_đảm an_toàn trong vận_chuyển .

8 . Phải theo sự hướng_dẫn của đơn_vị trực_tiếp_quản_lí hoặc đơn_vị thi_công khi vận_chuyển hàng_hoá nguy_hiểm là chất dễ cháy , chất dễ tự bốc cháy , chất_nổ lỏng hoặc rắn khử nhạy đi qua các công_trình cầu , hầm đặc_biệt quan_trọng có chiều dài dưới 100m hoặc các công_trình khác đang được thi_công có nhiệt_độ cao , lửa hàn , tia lửa điện trên hành_trình vận_chuyển .

9 . Phải có phương_án ứng_cứu sự_cố tràn dầu khi vận_tải xăng , dầu trên đường_thuỷ nội_địa .

10 . Tổ_chức huấn_luyện hoặc thuê đơn_vị có chức_năng huấn_luyện an_toàn hàng_hoá nguy_hiểm đối_với người điều_khiển phương_tiện theo quy_định tại Điều 8 của Nghị_định này .

Điều 33 . Đối_với người điều_khiển phương_tiện , người áp_tải

1 . Chấp_hành các quy_định ghi trong Giấy_phép và chỉ được tổ_chức vận_chuyển hàng_hoá nguy_hiểm khi : Có Giấy_phép vận_chuyển hàng_hoá nguy_hiểm còn hiệu_lực đối_với loại , nhóm , tên hàng_hoá quy_định phải có Giấy_phép ; trên phương , bao_bì , thùng chứa có đầy_đủ biểu_trưng , báo_hiệu nguy_hiểm .

2 . Thực_hiện chỉ_dẫn ghi trong thông_báo của người thuê vận_tải hàng_hoá nguy_hiểm và chỉ_dẫn của người vận_tải hàng_hoá nguy_hiểm .

3 . Phải theo sự hướng_dẫn của đơn_vị trực_tiếp_quản_lí hoặc đơn_vị thi_công khi vận_chuyển hàng_hoá nguy_hiểm là chất dễ cháy , chất dễ tự bốc cháy , chất_nổ lỏng hoặc đặc khử nhạy đi qua các công_trình cầu , hầm đặc_biệt quan_trọng hoặc các công_trình khác đang được thi_công có nhiệt_độ cao , lửa hàn , tia lửa điện trên hành_trình vận_chuyển .

4 . Người điều_khiển phương_tiện phải mang theo hồ_sơ vận_chuyển hàng_hoá nguy_hiểm do người thuê vận_tải cung_cấp , Giấy_phép vận_chuyển hàng_hoá nguy_hiểm còn hiệu_lực đối_với loại , nhóm , tên hàng_hoá quy_định phải có Giấy_phép , Giấy chứng_nhận đã hoàn_thành huấn_luyện an_toàn hàng_hoá nguy_hiểm phù_hợp với loại , nhóm hàng nguy_hiểm đang vận_chuyển , chứng_chỉ chuyên_môn đặc_biệt ( áp_dụng đối_với thuyền_trưởng hoặc người lái phương_tiện thuỷ nội_địa ) và các loại giấy khác theo quy_định của pháp_luật ; bảo_quản hàng_hoá nguy_hiểm trong quá_trình vận_chuyển khi không có người áp_tải hàng_hoá .

5 . Thực_hiện các biện_pháp loại_trừ hoặc hạn_chế khả_năng gây hại của hàng_hoá nguy_hiểm ; lập biên_bản , báo_cáo Ủy_ban nhân_dân địa_phương cấp xã nơi gần nhất và các cơ_quan liên_quan để xử_lí kịp_thời khi phát_hiện hàng_hoá nguy_hiểm có sự_cố , đe_doạ đến an_toàn của người , phương_tiện , môi_trường và hàng_hoá khác hoặc khi xảy ra tai_nạn giao_thông trong quá_trình vận_chuyển . Trường_hợp vượt quá khả_năng , phải báo ngay cho người vận_tải và người thuê vận_tải để cùng phối_hợp giải_quyết kịp_thời .

6 . Thuyền_trưởng hoặc người lái phương_tiện thuỷ nội_địa có trách_nhiệm phân_công thuyền_viên thường_xuyên hướng_dẫn , giám_sát việc xếp , dỡ hàng_hoá nguy_hiểm trên phương_tiện .

7 . Phải theo sự hướng_dẫn của đơn_vị trực_tiếp_quản_lí hoặc đơn_vị thi_công khi vận_chuyển hàng_hoá nguy_hiểm là chất dễ cháy , chất dễ tự bốc cháy , chất_nổ lỏng hoặc rắn khử nhạy đi qua các công_trình cầu , hầm đặc_biệt quan_trọng có chiều dài dưới 100m hoặc các công_trình khác đang được thi_công có nhiệt_độ cao , lửa hàn , tia lửa điện trên hành_trình vận_chuyển .

8 . Người áp_tải phải mang theo Giấy chứng_nhận đã hoàn_thành huấn_luyện hàng_hoá nguy_hiểm phù_hợp với loại , nhóm hàng nguy_hiểm đang vận_chuyển .

Chương_vi

Điều_khoản Thi_hành

Điều 34 . Hiệu_lực thi_hành

1 . Nghị_định này có hiệu_lực thi_hành kể từ ngày 15 tháng 5 năm 2024 và thay_thế <NĐ rel="None"> Nghị_định số 42/2020/NĐ-CP </NĐ>, ngày 08 tháng 4 năm 2020 của Chính_phủ quy_định_danh_mục hàng_hoá nguy_hiểm , vận_chuyển hàng_hoá nguy_hiểm bằng phương_tiện giao_thông cơ_giới đường_bộ và vận_chuyển hàng_hoá nguy_hiểm trên đường_thuỷ nội_địa .

2 . Các tổ_chức , cá_nhân đã được cấp Giấy_phép vận_chuyển hàng_hoá nguy_hiểm trước ngày Nghị_định này có hiệu_lực thi_hành tiếp_tục được sử_dụng , không phải thực_hiện cấp lại cho đến khi hết hiệu_lực của Giấy_phép hoặc đến khi thực_hiện cấp lại .

Điều 35 . Trách_nhiệm thi_hành

Các Bộ_trưởng , Thủ_trưởng cơ_quan ngang bộ , Thủ_trưởng cơ_quan thuộc Chính_phủ , Chủ_tịch Ủy_ban nhân_dân tỉnh , thành_phố trực_thuộc trung_ương và các cá_nhân , đơn_vị có liên_quan chịu trách_nhiệm thi_hành Nghị_định này . / .
