Thông_tư số 56/2020/tt-btc ngày 12 tháng 06 năm 2020 của bộ tài_chính

Căn_cứ <LT rel="CC"> Luật Phí và lệ_phí ngày 25 tháng 11 năm 2015 </LT> ;

Căn_cứ <NĐ rel="CC"> Nghị_định số 87/2017/NĐ-CP ngày 26 tháng 7 năm 2017 </NĐ> của Chính_phủ quy_định chức_năng , nhiệm_vụ , quyền_hạn và cơ_cấu tổ_chức của Bộ Tài_chính ;

Thực_hiện <CT rel="None"> Chỉ_thị số 11/CT-TTg ngày 04 tháng 3 năm 2020 </CT> của Thủ_tướng Chính_phủ về các nhiệm_vụ , giải_pháp cấp_bách tháo_gỡ khó_khăn cho sản_xuất kinh_doanh , bảo_đảm an_sinh xã_hội ứng_phó với dịch Covid - 19 ;

Theo đề_nghị của Vụ_trưởng Vụ Chính_sách thuế ;

Bộ_trưởng Bộ Tài_chính ban_hành <TT rel="None"> Thông_tư quy_định mức thu </TT> , nộp phí , lệ_phí trong lĩnh_vực trồng_trọt và giống cây lâm_nghiệp .

Điều 1 . Mức thu , nộp phí , lệ_phí trong lĩnh_vực trồng_trọt và giống cây lâm_nghiệp

1 . Tổ_chức , cá_nhân khi đề_nghị cơ_quan nhà_nước có thẩm_quyền cấp văn_bằng bảo_hộ , cấp chứng_nhận đăng_kí hợp_đồng chuyển_giao quyền sở_hữu công_nghiệp ; nộp đơn đăng_kí bảo_hộ quyền sở_hữu trí_tuệ ; cấp chứng_chỉ hành_nghề đại_diện sở_hữu công_nghiệp , công_bố , đăng bạ đại_diện sở_hữu công_nghiệp thực_hiện nộp lệ_phí như sau :

a ) Kể từ ngày Thông_tư này có hiệu_lực thi_hành đến hết ngày 31 tháng 12 năm 2020 , nộp lệ_phí bằng 50 % mức thu quy_định tại Mục I Biểu phí , lệ_phí trong lĩnh_vực trồng_trọt và giống cây lâm_nghiệp ban_hành kèm theo <TT rel="DC"> Thông_tư số 207/2016/TT-BTC ngày 09 tháng 11 năm 2016 </TT> của Bộ_trưởng Bộ Tài_chính quy_định mức thu , chế_độ thu , nộp , quản_lí và sử_dụng phí , lệ_phí trong lĩnh_vực trồng_trọt và giống cây lâm_nghiệp ( sau đây gọi là <TT rel="DC"> Thông_tư số 207/2016/TT-BTC </TT>).

Trong thời_gian có hiệu_lực của Thông_tư này , không nộp lệ_phí trong lĩnh_vực trồng_trọt và giống cây lâm_nghiệp theo mức thu quy_định tại Mục I Biểu phí , lệ_phí trong lĩnh_vực trồng_trọt và giống cây lâm_nghiệp ban_hành kèm theo <TT rel="DC"> Thông_tư số 207/2016/TT-BTC </TT>.

b ) Kể từ ngày 01 tháng 01 năm 2021 trở_đi , nộp lệ_phí trong lĩnh_vực trồng_trọt và giống cây lâm_nghiệp theo mức thu quy_định tại Mục I Biểu phí , lệ_phí trong lĩnh_vực trồng_trọt và giống cây lâm_nghiệp ban_hành kèm theo <TT rel="DC"> Thông_tư số 207/2016/TT-BTC </TT>.

2 . Tổ_chức , cá_nhân khi nộp đơn yêu_cầu cơ_quan nhà_nước có thẩm_quyền bảo_hộ giống cây_trồng ( duy_trì hiệu_lực Bằng bảo_hộ giống cây_trồng ) thực_hiện nộp phí như sau :

a ) Kể từ ngày Thông_tư này có hiệu_lực thi_hành đến hết ngày 31 tháng 12 năm 2020

- Trường_hợp duy_trì hiệu_lực Bằng bảo_hộ giống cây_trồng từ năm thứ 1 đến năm thứ 9 , nộp phí bằng 80 % mức thu quy_định tại Điểm 3 Mục_iii Biểu phí , lệ_phí trong lĩnh_vực trồng_trọt và giống cây lâm_nghiệp ban_hành kèm theo <TT rel="DC"> Thông_tư số 207/2016/TT-BTC </TT>.

- Trường_hợp duy_trì hiệu_lực Bằng bảo_hộ giống cây_trồng từ năm thứ 10 đến hết thời_gian hiệu_lực của Bằng bảo_hộ , nộp phí bằng 70 % mức thu quy_định tại Điểm 3 Mục_iii Biểu phí , lệ_phí trong lĩnh_vực trồng_trọt và giống cây lâm_nghiệp ban_hành kèm theo <TT rel="DC"> Thông_tư số 207/2016/TT-BTC </TT>.

Trong thời_gian có hiệu_lực của Thông_tư này , không nộp phí bảo_hộ giống cây_trồng đối_với trường_hợp duy_trì hiệu_lực Bằng bảo_hộ giống cây_trồng theo mức phí quy_định tại Điểm 3 Mục_iii Biểu phí , lệ_phí trong lĩnh_vực trồng_trọt và giống cây lâm_nghiệp ban_hành kèm theo <TT rel="DC"> Thông_tư số 207/2016/TT-BTC </TT> .

b ) Kể từ ngày 01 tháng 01 năm 2021 trở_đi , nộp phí bảo_hộ giống cây_trồng đối_với trường_hợp duy_trì hiệu_lực Bằng bảo_hộ giống cây_trồng theo mức thu quy_định tại Điểm 3 Mục_iii Biểu phí , lệ_phí trong lĩnh_vực trồng_trọt và giống cây lâm_nghiệp ban_hành kèm theo <TT rel="DC"> Thông_tư số 207/2016/TT-BTC </TT>.

Điều 2 . Hiệu_lực thi_hành

1 . Thông_tư này có hiệu_lực thi_hành kể từ ngày 12 tháng 6 năm 2020 đến hết ngày 31 tháng 12 năm 2020 .

2 . Các nội_dung về phạm_vi điều_chỉnh , đối_tượng áp_dụng , người nộp , tổ_chức thu , mức thu , kê_khai , nộp phí , lệ_phí ; quản_lý , sử_dụng phí ; chứng_từ thu , công_khai chế_độ thu phí , lệ_phí và các nội_dung khác liên_quan không quy_định tại Thông_tư này thực_hiện theo quy_định tại <TT rel="DC"> Thông_tư số 207/2016/TT-BTC </TT>.

3 . Trong quá_trình thực_hiện , nếu có vướng_mắc đề_nghị các tổ_chức , cá_nhân phản_ánh kịp_thời về Bộ Tài_chính để nghiên_cứu , hướng_dẫn bổ_sung . / .
